morphapiwrapper/__init__.py
morphapiwrapper/gcsbase.py
morphapiwrapper/testscript.py
morphapiwrapper-1.0.dist-info/LICENSE
morphapiwrapper-1.0.dist-info/METADATA
morphapiwrapper-1.0.dist-info/WHEEL
morphapiwrapper-1.0.dist-info/top_level.txt
morphapiwrapper-1.0.dist-info/RECORD
