Metadata-Version: 2.1
Name: morphapiwrapper
Version: 1.0
Summary: Wrapper functions for creating APIs in Morphisdom
Home-page: https://github.com/morphisdom/morphapiwrapper
Author: Morphisdom
Author-email: info@morphisdom.com
Project-URL: Bug Tracker, https://github.com/morphisdom/morphapiwrapper/issues
Keywords: API constructor,Flask API,Google cloud storage base,microservices
Classifier: Programming Language :: Python :: 3
Classifier: License :: OSI Approved :: MIT License
Classifier: Operating System :: OS Independent
Requires-Python: >=3.6
License-File: LICENSE
Requires-Dist: flask
Requires-Dist: requests
Requires-Dist: google-cloud-storage
Requires-Dist: google-auth
